mylib_012/__init__.py
mylib_012-0.1.dist-info/LICENSE.txt
mylib_012-0.1.dist-info/METADATA
mylib_012-0.1.dist-info/WHEEL
mylib_012-0.1.dist-info/top_level.txt
mylib_012-0.1.dist-info/RECORD
