Metadata-Version: 2.1
Name: mylib-012
Version: 0.1
Summary: for calculating square
Author: Anshal
Author-email: anshaltripathi1999@gmail.com
Classifier: Programming Language :: Python :: 3
Classifier: License :: OSI Approved :: MIT License
Classifier: Operating System :: OS Independent
License-File: LICENSE.txt
